MolPainter/MolSolvator.py
MolPainter/__init__.py
MolPainter/about_dialog.py
MolPainter/blend_configurator.py
MolPainter/cmdbar.py
MolPainter/commands.py
MolPainter/drawarea.py
MolPainter/exporter.py
MolPainter/grid_configurator.py
MolPainter/layer_configurator.py
MolPainter/layer_painter.py
MolPainter/molecule_configurator.py
MolPainter/molecule_lister.py
MolPainter/painter.py
MolPainter/proj_saver.py
MolPainter/project.py
MolPainter/solute_importer.py
MolPainter/toolbox.py
MolPainter/icons/pencil.png
MolPainter/icons/spraycan.png
MolPainter/icons/square.png
MolPainter/icons/zoomin.png
MolPainter/icons/zoomout.png
MolPainter_gpantel-1.1.3.dist-info/LICENSE
MolPainter_gpantel-1.1.3.dist-info/METADATA
MolPainter_gpantel-1.1.3.dist-info/WHEEL
MolPainter_gpantel-1.1.3.dist-info/entry_points.txt
MolPainter_gpantel-1.1.3.dist-info/top_level.txt
MolPainter_gpantel-1.1.3.dist-info/RECORD
